MANIFEST.in
README.md
base.cfg
requirements-4.3.txt
requirements-5.2.txt
setup.cfg
setup.py
test-4.3.cfg
test-5.2.cfg
docs/HISTORY.txt
docs/INSTALL.txt
docs/LICENSE.GPL
docs/LICENSE.txt
slc/__init__.py
slc.mail2news.egg-info/PKG-INFO
slc.mail2news.egg-info/SOURCES.txt
slc.mail2news.egg-info/dependency_links.txt
slc.mail2news.egg-info/entry_points.txt
slc.mail2news.egg-info/namespace_packages.txt
slc.mail2news.egg-info/not-zip-safe
slc.mail2news.egg-info/requires.txt
slc.mail2news.egg-info/top_level.txt
slc/mail2news/__init__.py
slc/mail2news/configure.zcml
slc/mail2news/interfaces.py
slc/mail2news/scripts.py
slc/mail2news/testing.py
slc/mail2news/browser/__init__.py
slc/mail2news/browser/configure.zcml
slc/mail2news/browser/mailhandler.py
slc/mail2news/tests/__init__.py
slc/mail2news/tests/mail_8bit.txt
slc/mail2news/tests/mail_mixed.txt
slc/mail2news/tests/mail_plain.txt
slc/mail2news/tests/mail_plain_ignore.txt
slc/mail2news/tests/mail_plain_with_image.txt
slc/mail2news/tests/mail_quoted_printable.txt
slc/mail2news/tests/mail_sender_utf8.txt
slc/mail2news/tests/mail_subject_utf8.txt
slc/mail2news/tests/test_views.py