Metadata-Version: 2.1
Name: slc.mail2news
Version: 2.0.1
Summary: Transfers emails to Plone news items
Home-page: http://syslab.com/
Author: Syslab.com
Author-email: info@syslab.com
License: GPL
Keywords: mail news rpc
Platform: UNKNOWN
Classifier: Development Status :: 5 - Production/Stable
Classifier: Framework :: Plone
Classifier: Framework :: Plone :: 4.3
Classifier: Framework :: Plone :: 5.2
Classifier: License :: OSI Approved :: GNU General Public License v2 or later (GPLv2+)
Classifier: Programming Language :: Python
Classifier: Programming Language :: Python :: 2.7
Classifier: Programming Language :: Python :: 3.7
Provides-Extra: test
